reddit_chats/__init__.py
reddit_chats/api.py
reddit_chats/auth.py
reddit_chats-0.0.5.dist-info/METADATA
reddit_chats-0.0.5.dist-info/WHEEL
reddit_chats-0.0.5.dist-info/licenses/LICENSE
reddit_chats-0.0.5.dist-info/RECORD
