Metadata-Version: 2.3
Name: reddit_chats
Version: 0.0.5
Summary: Reddit Chats SDK for chat bots
Project-URL: Homepage, https://www.reddit.com/r/redditChatBots/
Project-URL: Issues, https://www.reddit.com/r/redditChatBots/
Author-email: xwizard707 <timurnurlygayanov@mail.ru>, koalascala <timurkhasanov.tk@gmail.com>
License-File: LICENSE
Classifier: License :: OSI Approved :: MIT License
Classifier: Operating System :: OS Independent
Classifier: Programming Language :: Python :: 3
Requires-Python: >=3.8
Requires-Dist: asyncio
Requires-Dist: latest-user-agents
Requires-Dist: matrix-nio
Requires-Dist: requests
